lambdatest_tunnel/__init__.py
lambdatest_tunnel/lt_errors.py
lambdatest_tunnel/tunnel.py
lambdatest_tunnel/tunnel_binary.py
lambdatest_tunnel-0.1.2.dist-info/LICENSE
lambdatest_tunnel-0.1.2.dist-info/METADATA
lambdatest_tunnel-0.1.2.dist-info/WHEEL
lambdatest_tunnel-0.1.2.dist-info/top_level.txt
lambdatest_tunnel-0.1.2.dist-info/RECORD
