Metadata-Version: 2.1
Name: lambdatest-tunnel
Version: 0.1.2
Summary: Plugin to start / stop LambdaTest Tunnel for local testing
Home-page: https://github.com/uprichard/lambdatest-tunnel-manager
Author: Nigel Uprichard
Author-email: uprichard@users.noreply.github.com
License: MIT
Keywords: testing,selenium,driver,test automation,lamdatest
Platform: UNKNOWN
Classifier: Development Status :: 4 - Beta
Classifier: Intended Audience :: Developers
Classifier: Natural Language :: English
Classifier: License :: OSI Approved :: MIT License
Classifier: Programming Language :: Python
Classifier: Programming Language :: Python :: 3
Requires-Python: >=3.6
Requires-Dist: requests
